magick_tile/__init__.py
magick_tile/generator.py
magick_tile/main.py
magick_tile/manifest.py
magick_tile/py.typed
magick_tile/settings.py
magick_tile-0.1.1.dist-info/entry_points.txt
magick_tile-0.1.1.dist-info/LICENSE
magick_tile-0.1.1.dist-info/WHEEL
magick_tile-0.1.1.dist-info/METADATA
magick_tile-0.1.1.dist-info/RECORD
